[
  {
    "position": "Software Engineer III",
    "company": "American Express",
    "location": "Chennai, Tamil Nadu, India",
    "date": "2025-07-18",
    "salary": "Not specified",
    "jobUrl": "https://in.linkedin.com/jobs/view/software-engineer-iii-at-american-express-4269131102?position=1&pageNum=0&refId=Xoj%2BgGuc5ECXk1xZLCPc8Q%3D%3D&trackingId=5DvSzSMFt%2Fv8sf%2Fsy01nNQ%3D%3D",
    "companyLogo": "https://media.licdn.com/dms/image/v2/C4D0BAQGRhsociEn4gQ/company-logo_100_100/company-logo_100_100/0/1631367875582?e=2147483647&v=beta&t=bk_i8KnJwZyUrbBXvWK0NMb6W3nPq64rupEGTrKvxYU",
    "agoTime": "1 day ago",
    "metadata": {
      "keyword": "Digital ASIC Engineer",
      "location": "Chennai",
      "experienceLevel": "Chief Technology Officer",
      "remoteFilter": "hybrid"
    }
  },
  {
    "position": "Engineer I",
    "company": "American Express",
    "location": "Chennai, Tamil Nadu, India",
    "date": "2025-07-18",
    "salary": "Not specified",
    "jobUrl": "https://in.linkedin.com/jobs/view/engineer-i-at-american-express-4269513260?position=2&pageNum=0&refId=Xoj%2BgGuc5ECXk1xZLCPc8Q%3D%3D&trackingId=IWNVZP6FjVkpW7eOnIcYEQ%3D%3D",
    "companyLogo": "https://media.licdn.com/dms/image/v2/C4D0BAQGRhsociEn4gQ/company-logo_100_100/company-logo_100_100/0/1631367875582?e=2147483647&v=beta&t=bk_i8KnJwZyUrbBXvWK0NMb6W3nPq64rupEGTrKvxYU",
    "agoTime": "1 day ago",
    "metadata": {
      "keyword": "Digital ASIC Engineer",
      "location": "Chennai",
      "experienceLevel": "Chief Technology Officer",
      "remoteFilter": "hybrid"
    }
  },
  {
    "position": "Software Engineer",
    "company": "Arista Networks",
    "location": "Chennai, Tamil Nadu, India",
    "date": "2025-07-17",
    "salary": "Not specified",
    "jobUrl": "https://in.linkedin.com/jobs/view/software-engineer-at-arista-networks-4266946926?position=3&pageNum=0&refId=Xoj%2BgGuc5ECXk1xZLCPc8Q%3D%3D&trackingId=Mk1FIId95FJNP%2BdMcc2feg%3D%3D",
    "companyLogo": "https://media.licdn.com/dms/image/v2/C560BAQGkAHWhvOGQbA/company-logo_100_100/company-logo_100_100/0/1631359666583?e=2147483647&v=beta&t=XeYwctubA9hp5FP3rPks0_AMYJYXB-5_9hGo80XvRQM",
    "agoTime": "2 days ago",
    "metadata": {
      "keyword": "Digital ASIC Engineer",
      "location": "Chennai",
      "experienceLevel": "Chief Technology Officer",
      "remoteFilter": "hybrid"
    }
  },
  {
    "position": "Software Engineer III",
    "company": "Walmart Global Tech India",
    "location": "Chennai, Tamil Nadu, India",
    "date": "2025-07-19",
    "salary": "Not specified",
    "jobUrl": "https://in.linkedin.com/jobs/view/software-engineer-iii-at-walmart-global-tech-india-4242455417?position=4&pageNum=0&refId=Xoj%2BgGuc5ECXk1xZLCPc8Q%3D%3D&trackingId=g95PWBnmAP4Zut1NlULGaA%3D%3D",
    "companyLogo": "https://media.licdn.com/dms/image/v2/C4D0BAQEC3n4yU_w6bQ/company-logo_100_100/company-logo_100_100/0/1630541053165/walmartglobaltechindia_logo?e=2147483647&v=beta&t=KB5uAZVI1HRhFi7_oz2n8i2VD4Sx9DcqRNE-fpD1_zY",
    "agoTime": "",
    "metadata": {
      "keyword": "Digital ASIC Engineer",
      "location": "Chennai",
      "experienceLevel": "Chief Technology Officer",
      "remoteFilter": "hybrid"
    }
  },
  {
    "position": "Data Analyst",
    "company": "Deloitte",
    "location": "Chennai, Tamil Nadu, India",
    "date": "2025-07-18",
    "salary": "Not specified",
    "jobUrl": "https://in.linkedin.com/jobs/view/data-analyst-at-deloitte-4267803159?position=5&pageNum=0&refId=Xoj%2BgGuc5ECXk1xZLCPc8Q%3D%3D&trackingId=VXneg214jcSKy4QVg0eBkw%3D%3D",
    "companyLogo": "https://media.licdn.com/dms/image/v2/C560BAQGNtpblgQpJoQ/company-logo_100_100/company-logo_100_100/0/1662120928214/deloitte_logo?e=2147483647&v=beta&t=OSF8M5LreT0Sf2F-JcNk6XMT0ArCuPfDmRR-knCC4HY",
    "agoTime": "",
    "metadata": {
      "keyword": "Digital ASIC Engineer",
      "location": "Chennai",
      "experienceLevel": "Chief Technology Officer",
      "remoteFilter": "hybrid"
    }
  },
  {
    "position": "Software Engineer II",
    "company": "Alation",
    "location": "Greater Chennai Area",
    "date": "2025-07-18",
    "salary": "Not specified",
    "jobUrl": "https://in.linkedin.com/jobs/view/software-engineer-ii-at-alation-4267452847?position=6&pageNum=0&refId=Xoj%2BgGuc5ECXk1xZLCPc8Q%3D%3D&trackingId=kaMVeWSesLPzRbGSZ8mCsg%3D%3D",
    "companyLogo": "https://media.licdn.com/dms/image/v2/D560BAQHAeTuyeaeFUQ/company-logo_100_100/company-logo_100_100/0/1726324067602/alation_logo?e=2147483647&v=beta&t=9vIseiTzDw0zH6f7D1pZ0c0vkF4_5pnXIHiW-9o-pJk",
    "agoTime": "1 day ago",
    "metadata": {
      "keyword": "Digital ASIC Engineer",
      "location": "Chennai",
      "experienceLevel": "Chief Technology Officer",
      "remoteFilter": "hybrid"
    }
  },
  {
    "position": "Software Engineer",
    "company": "Alation",
    "location": "Greater Chennai Area",
    "date": "2025-07-18",
    "salary": "Not specified",
    "jobUrl": "https://in.linkedin.com/jobs/view/software-engineer-at-alation-4267449956?position=7&pageNum=0&refId=Xoj%2BgGuc5ECXk1xZLCPc8Q%3D%3D&trackingId=1xGzYjXBjJ3uFO0LtstyEQ%3D%3D",
    "companyLogo": "https://media.licdn.com/dms/image/v2/D560BAQHAeTuyeaeFUQ/company-logo_100_100/company-logo_100_100/0/1726324067602/alation_logo?e=2147483647&v=beta&t=9vIseiTzDw0zH6f7D1pZ0c0vkF4_5pnXIHiW-9o-pJk",
    "agoTime": "1 day ago",
    "metadata": {
      "keyword": "Digital ASIC Engineer",
      "location": "Chennai",
      "experienceLevel": "Chief Technology Officer",
      "remoteFilter": "hybrid"
    }
  },
  {
    "position": "Director Enterprise Architecture",
    "company": "Ford Motor Company",
    "location": "Chennai, Tamil Nadu, India",
    "date": "2025-07-15",
    "salary": "Not specified",
    "jobUrl": "https://in.linkedin.com/jobs/view/director-enterprise-architecture-at-ford-motor-company-4266735911?position=8&pageNum=0&refId=Xoj%2BgGuc5ECXk1xZLCPc8Q%3D%3D&trackingId=MuO9iUgDp6hopuoGO5LV%2FQ%3D%3D",
    "companyLogo": "https://media.licdn.com/dms/image/v2/C560BAQHZnQf3t8fKKg/company-logo_100_100/company-logo_100_100/0/1630670609155/ford_motor_company_logo?e=2147483647&v=beta&t=RJaj5pQAZB9Jvw_djO71CdhBJVBlOH7NLolHoWLOxJQ",
    "agoTime": "3 days ago",
    "metadata": {
      "keyword": "Digital ASIC Engineer",
      "location": "Chennai",
      "experienceLevel": "Chief Technology Officer",
      "remoteFilter": "hybrid"
    }
  },
  {
    "position": "(IND) SENIOR, SOFTWARE ENGINEER",
    "company": "Walmart Global Tech India",
    "location": "Chennai, Tamil Nadu, India",
    "date": "2025-07-17",
    "salary": "Not specified",
    "jobUrl": "https://in.linkedin.com/jobs/view/ind-senior-software-engineer-at-walmart-global-tech-india-4266924435?position=9&pageNum=0&refId=Xoj%2BgGuc5ECXk1xZLCPc8Q%3D%3D&trackingId=%2FGoR%2B2ashggmrO7znUAM1g%3D%3D",
    "companyLogo": "https://media.licdn.com/dms/image/v2/C4D0BAQEC3n4yU_w6bQ/company-logo_100_100/company-logo_100_100/0/1630541053165/walmartglobaltechindia_logo?e=2147483647&v=beta&t=KB5uAZVI1HRhFi7_oz2n8i2VD4Sx9DcqRNE-fpD1_zY",
    "agoTime": "2 days ago",
    "metadata": {
      "keyword": "Digital ASIC Engineer",
      "location": "Chennai",
      "experienceLevel": "Chief Technology Officer",
      "remoteFilter": "hybrid"
    }
  },
  {
    "position": "Software Engineer",
    "company": "NatWest Group",
    "location": "Chennai, Tamil Nadu, India",
    "date": "2025-07-15",
    "salary": "Not specified",
    "jobUrl": "https://in.linkedin.com/jobs/view/software-engineer-at-natwest-group-4267175607?position=10&pageNum=0&refId=Xoj%2BgGuc5ECXk1xZLCPc8Q%3D%3D&trackingId=Cr6dga1rxUgzgPaPDiwGTQ%3D%3D",
    "companyLogo": "https://media.licdn.com/dms/image/v2/C4E0BAQEA8k9x0NLXVw/company-logo_100_100/company-logo_100_100/0/1658409007559/natwest_group_logo?e=2147483647&v=beta&t=77U4pn7D2sdoWVtDxd-1OFNiFco375nnYIWapD6QRBA",
    "agoTime": "4 days ago",
    "metadata": {
      "keyword": "Digital ASIC Engineer",
      "location": "Chennai",
      "experienceLevel": "Chief Technology Officer",
      "remoteFilter": "hybrid"
    }
  }
]
