[
  {
    "position": "Program Head - AI & Quantam",
    "company": "Wadhwani Foundation",
    "location": "Delhi, Delhi, India",
    "date": "2025-07-17",
    "salary": "Not specified",
    "jobUrl": "https://in.linkedin.com/jobs/view/program-head-ai-quantam-at-wadhwani-foundation-4266958363?refId=xHMGqmnN2e8C%2BvgKC96MRA%3D%3D&trackingId=feA7%2BEsxUF74UklN%2FfuqbQ%3D%3D&position=1&pageNum=0",
    "companyLogo": "https://media.licdn.com/dms/image/v2/D560BAQEId7o5kiEw_w/company-logo_100_100/company-logo_100_100/0/1707208630321/wadhwanifoundation_logo?e=1755734400&v=beta&t=YDjso0e0XUvA6P9oTzBLyxphBUAP85WbFUX7S1HmxME",
    "agoTime": "2 days ago",
    "metadata": {
      "keyword": "Quantum Hardware Engineer",
      "location": "Noida",
      "experienceLevel": "Director",
      "remoteFilter": "hybrid"
    }
  },
  {
    "position": "Enterprise Employer Relationship Head",
    "company": "Wadhwani Foundation",
    "location": "Delhi, Delhi, India",
    "date": "2025-07-16",
    "salary": "Not specified",
    "jobUrl": "https://in.linkedin.com/jobs/view/enterprise-employer-relationship-head-at-wadhwani-foundation-4266419611?position=1&pageNum=2&refId=4OiEgU2LSoJDaouK8%2FGGPg%3D%3D&trackingId=%2F3RTON0o%2F2%2FaPpqT8mGxhA%3D%3D",
    "companyLogo": "https://media.licdn.com/dms/image/v2/D560BAQEId7o5kiEw_w/company-logo_100_100/company-logo_100_100/0/1707208630321/wadhwanifoundation_logo?e=2147483647&v=beta&t=7j_q1Y__oic65Jqs5wJIPuGTcTjsVUFI69fizbTsCG0",
    "agoTime": "3 days ago",
    "metadata": {
      "keyword": "Quantum Hardware Engineer",
      "location": "Noida",
      "experienceLevel": "Director",
      "remoteFilter": "hybrid"
    }
  }
]
