[
  {
    "position": "Back End Developer",
    "company": "Zoho",
    "location": "Chennai, Tamil Nadu, India",
    "date": "2025-07-18",
    "salary": "Not specified",
    "jobUrl": "https://in.linkedin.com/jobs/view/back-end-developer-at-zoho-4269506377?position=1&pageNum=0&refId=00aYBmzwhup8GNoB2JHHqQ%3D%3D&trackingId=GFksMYr3TnS%2FtpcXQKMUmQ%3D%3D",
    "companyLogo": "https://media.licdn.com/dms/image/v2/D560BAQHIJEEams6Ghg/company-logo_100_100/company-logo_100_100/0/1735737146960/zoho_logo?e=2147483647&v=beta&t=l4bwBFsJO_7sMogO7JffLnFEw7ZLKIV8sbiBVe0cjw4",
    "agoTime": "1 day ago",
    "metadata": {
      "keyword": "Quantum Computing Engineer",
      "location": "Chennai",
      "experienceLevel": "Chief Technology Officer",
      "remoteFilter": "on-site"
    }
  },
  {
    "position": "Key Account Manager (Acquisition) - Chennai",
    "company": "MakeMyTrip",
    "location": "Chennai, Tamil Nadu, India",
    "date": "2025-07-14",
    "salary": "Not specified",
    "jobUrl": "https://in.linkedin.com/jobs/view/key-account-manager-acquisition-chennai-at-makemytrip-4266328550?position=2&pageNum=0&refId=00aYBmzwhup8GNoB2JHHqQ%3D%3D&trackingId=W%2FtLPf9%2BakXqRieC9Jn0XQ%3D%3D",
    "companyLogo": "https://media.licdn.com/dms/image/v2/C4E0BAQGztBPTPiyXdA/company-logo_100_100/company-logo_100_100/0/1630583346942/makemytripcom_logo?e=2147483647&v=beta&t=fOMvG6edzf1FAZGLRA3F67uqaB-y0OFFCYoOlAHLD00",
    "agoTime": "5 days ago",
    "metadata": {
      "keyword": "Quantum Computing Engineer",
      "location": "Chennai",
      "experienceLevel": "Chief Technology Officer",
      "remoteFilter": "on-site"
    }
  },
  {
    "position": "Software Engineer – Python",
    "company": "PayPal",
    "location": "Chennai, Tamil Nadu, India",
    "date": "2025-07-15",
    "salary": "Not specified",
    "jobUrl": "https://in.linkedin.com/jobs/view/software-engineer-%E2%80%93-python-at-paypal-4257694446?position=3&pageNum=0&refId=00aYBmzwhup8GNoB2JHHqQ%3D%3D&trackingId=xzIZ1%2BGGfF%2BCJM7dDsRzXQ%3D%3D",
    "companyLogo": "https://media.licdn.com/dms/image/v2/D560BAQGlX0cKdGRk-w/company-logo_100_100/company-logo_100_100/0/1725506319701?e=2147483647&v=beta&t=EfHoqyaVYveWMzdT_6PpJbGNGS1P4dUk3ZryqIQRhjc",
    "agoTime": "3 days ago",
    "metadata": {
      "keyword": "Quantum Computing Engineer",
      "location": "Chennai",
      "experienceLevel": "Chief Technology Officer",
      "remoteFilter": "on-site"
    }
  },
  {
    "position": "Associate",
    "company": "Ford Motor Company",
    "location": "Chennai, Tamil Nadu, India",
    "date": "2025-07-18",
    "salary": "Not specified",
    "jobUrl": "https://in.linkedin.com/jobs/view/associate-at-ford-motor-company-4269542067?position=4&pageNum=0&refId=00aYBmzwhup8GNoB2JHHqQ%3D%3D&trackingId=o6Nm%2BiCWBAYt7fn6luM0RA%3D%3D",
    "companyLogo": "https://media.licdn.com/dms/image/v2/C560BAQHZnQf3t8fKKg/company-logo_100_100/company-logo_100_100/0/1630670609155/ford_motor_company_logo?e=2147483647&v=beta&t=RJaj5pQAZB9Jvw_djO71CdhBJVBlOH7NLolHoWLOxJQ",
    "agoTime": "",
    "metadata": {
      "keyword": "Quantum Computing Engineer",
      "location": "Chennai",
      "experienceLevel": "Chief Technology Officer",
      "remoteFilter": "on-site"
    }
  },
  {
    "position": "Storage Administrator (Third Party role)",
    "company": "Jio",
    "location": "Chennai, Tamil Nadu, India",
    "date": "2025-07-17",
    "salary": "Not specified",
    "jobUrl": "https://in.linkedin.com/jobs/view/storage-administrator-third-party-role-at-jio-4267766999?position=5&pageNum=0&refId=00aYBmzwhup8GNoB2JHHqQ%3D%3D&trackingId=VLrs9Fx%2Fh6%2BKhh7gsCmOwg%3D%3D",
    "companyLogo": "https://media.licdn.com/dms/image/v2/C4D0BAQESqmIRc7VGFA/company-logo_100_100/company-logo_100_100/0/1655473519487/jio_logo?e=2147483647&v=beta&t=UB6VI3Z-jFxajyLsUfGCQH4VORUM0e8yec13wu2Yexg",
    "agoTime": "2 days ago",
    "metadata": {
      "keyword": "Quantum Computing Engineer",
      "location": "Chennai",
      "experienceLevel": "Chief Technology Officer",
      "remoteFilter": "on-site"
    }
  },
  {
    "position": "Finance Executive",
    "company": "A.P. Moller - Maersk",
    "location": "Greater Chennai Area",
    "date": "2025-07-17",
    "salary": "Not specified",
    "jobUrl": "https://in.linkedin.com/jobs/view/finance-executive-at-a-p-moller-maersk-4257406351?position=6&pageNum=0&refId=00aYBmzwhup8GNoB2JHHqQ%3D%3D&trackingId=sK1rh9fX4Ln12cUg1vbFhA%3D%3D",
    "companyLogo": "https://media.licdn.com/dms/image/v2/C4D0BAQFxaOJ8VzplhA/company-logo_100_100/company-logo_100_100/0/1630463556967/maersk_group_logo?e=2147483647&v=beta&t=YrP30ynaVz8K1BQU2Ap7mlV4Hx_xpRFYBVrVAd03m5A",
    "agoTime": "2 days ago",
    "metadata": {
      "keyword": "Quantum Computing Engineer",
      "location": "Chennai",
      "experienceLevel": "Chief Technology Officer",
      "remoteFilter": "on-site"
    }
  },
  {
    "position": "Site Incharge- SOLAR O&M",
    "company": "Larsen & Toubro",
    "location": "Chennai, Tamil Nadu, India",
    "date": "2025-07-14",
    "salary": "Not specified",
    "jobUrl": "https://in.linkedin.com/jobs/view/site-incharge-solar-o-m-at-larsen-toubro-4253237270?position=7&pageNum=0&refId=00aYBmzwhup8GNoB2JHHqQ%3D%3D&trackingId=e0OM6k4CvxiRkg0Qm3lDrQ%3D%3D",
    "companyLogo": "https://media.licdn.com/dms/image/v2/C4D0BAQFnEYpR8MlYsA/company-logo_100_100/company-logo_100_100/0/1631300737624?e=2147483647&v=beta&t=XwrPkxNIwc_l-G-D6Dfak1uo1oK-wEZfcwpUN3QD9WQ",
    "agoTime": "5 days ago",
    "metadata": {
      "keyword": "Quantum Computing Engineer",
      "location": "Chennai",
      "experienceLevel": "Chief Technology Officer",
      "remoteFilter": "on-site"
    }
  },
  {
    "position": "Execution, Chennai",
    "company": "Larsen & Toubro",
    "location": "Chennai, Tamil Nadu, India",
    "date": "2025-07-14",
    "salary": "Not specified",
    "jobUrl": "https://in.linkedin.com/jobs/view/execution-chennai-at-larsen-toubro-4237904230?position=8&pageNum=0&refId=00aYBmzwhup8GNoB2JHHqQ%3D%3D&trackingId=eGq%2F2fITnOZ5AN3b0cYnxg%3D%3D",
    "companyLogo": "https://media.licdn.com/dms/image/v2/C4D0BAQFnEYpR8MlYsA/company-logo_100_100/company-logo_100_100/0/1631300737624?e=2147483647&v=beta&t=XwrPkxNIwc_l-G-D6Dfak1uo1oK-wEZfcwpUN3QD9WQ",
    "agoTime": "5 days ago",
    "metadata": {
      "keyword": "Quantum Computing Engineer",
      "location": "Chennai",
      "experienceLevel": "Chief Technology Officer",
      "remoteFilter": "on-site"
    }
  },
  {
    "position": "Analyst, IT Infrastructure",
    "company": "Celestica",
    "location": "Guindy, Tamil Nadu, India",
    "date": "2025-07-17",
    "salary": "Not specified",
    "jobUrl": "https://in.linkedin.com/jobs/view/analyst-it-infrastructure-at-celestica-4078354827?position=9&pageNum=0&refId=00aYBmzwhup8GNoB2JHHqQ%3D%3D&trackingId=AoBoxxKgDNBt8mHUspd30Q%3D%3D",
    "companyLogo": "https://media.licdn.com/dms/image/v2/D560BAQH6r3QhxJozLg/company-logo_100_100/company-logo_100_100/0/1734384428585/celestica_logo?e=2147483647&v=beta&t=nZsa5fpGJXbzDddlohk2-mrm5phYf3AXgFkAMe0pzM8",
    "agoTime": "2 days ago",
    "metadata": {
      "keyword": "Quantum Computing Engineer",
      "location": "Chennai",
      "experienceLevel": "Chief Technology Officer",
      "remoteFilter": "on-site"
    }
  },
  {
    "position": "Device Associate I, Appstore",
    "company": "Amazon",
    "location": "Chennai, Tamil Nadu, India",
    "date": "2025-07-19",
    "salary": "Not specified",
    "jobUrl": "https://in.linkedin.com/jobs/view/device-associate-i-appstore-at-amazon-4245530067?position=10&pageNum=0&refId=00aYBmzwhup8GNoB2JHHqQ%3D%3D&trackingId=JScxywZz8upIjKVwRHDLSg%3D%3D",
    "companyLogo": "https://media.licdn.com/dms/image/v2/C560BAQHTvZwCx4p2Qg/company-logo_100_100/company-logo_100_100/0/1630640869849/amazon_logo?e=2147483647&v=beta&t=QsC16wgE3EBriPFDlAgtToh2xndFwQWKmR2WcyMG1nk",
    "agoTime": "",
    "metadata": {
      "keyword": "Quantum Computing Engineer",
      "location": "Chennai",
      "experienceLevel": "Chief Technology Officer",
      "remoteFilter": "on-site"
    }
  }
]
